etautil/__init__.py
etautil/constants.py
etautil/eta.py
etautil/time.py
etautil-3.0.0.dist-info/LICENSE
etautil-3.0.0.dist-info/WHEEL
etautil-3.0.0.dist-info/METADATA
etautil-3.0.0.dist-info/RECORD
